LICENSE
MANIFEST.in
README.md
setup.cfg
setup.py
python_wns.egg-info/PKG-INFO
python_wns.egg-info/SOURCES.txt
python_wns.egg-info/dependency_links.txt
python_wns.egg-info/pbr.json
python_wns.egg-info/requires.txt
python_wns.egg-info/top_level.txt
wns/__init__.py
wns/wnslib.py