Metadata-Version: 1.1
Name: python-wns
Version: 0.1
Summary: wns python library
Home-page: UNKNOWN
Author: Neetu Jain
Author-email: UNKNOWN
License: BSD License
Platform: UNKNOWN
Classifier: Development Status :: 4 - Beta
Classifier: Programming Language :: Python :: 2.7
